azure/core/tracing/ext/opentelemetry_span/__init__.py
azure/core/tracing/ext/opentelemetry_span/_schema.py
azure/core/tracing/ext/opentelemetry_span/_version.py
azure/core/tracing/ext/opentelemetry_span/py.typed
azure_core_tracing_opentelemetry-1.0.0b11.dist-info/LICENSE
azure_core_tracing_opentelemetry-1.0.0b11.dist-info/METADATA
azure_core_tracing_opentelemetry-1.0.0b11.dist-info/WHEEL
azure_core_tracing_opentelemetry-1.0.0b11.dist-info/top_level.txt
azure_core_tracing_opentelemetry-1.0.0b11.dist-info/RECORD
